AUTHORS
README.md
bitmapist/__init__.py
bitmapist/py.typed
bitmapist/cohort/__init__.py
bitmapist/cohort/tmpl/form_data.mako
bitmapist/cohort/tmpl/table_data.mako
bitmapist/cohort/tmpl/table_data_csv.mako
static/bitmapist.png
static/bitmapist.svg
bitmapist-3.119.dist-info/METADATA
bitmapist-3.119.dist-info/WHEEL
bitmapist-3.119.dist-info/licenses/AUTHORS
bitmapist-3.119.dist-info/licenses/LICENSE
bitmapist-3.119.dist-info/RECORD
