Metadata-Version: 2.4
Name: bitmapist
Version: 3.119
Summary: Implements a powerful analytics library using Redis bitmaps.
Project-URL: Repository, https://github.com/Doist/bitmapist
Author-email: Amir Salihefendic <dev@doist.com>, Doist Developers <dev@doist.com>
License-Expression: BSD-3-Clause
License-File: AUTHORS
License-File: LICENSE
Keywords: analytics,bitmap,bitmaps,cohort,realtime,redis
Classifier: Development Status :: 5 - Production/Stable
Classifier: Intended Audience :: Developers
Classifier: Operating System :: OS Independent
Classifier: Programming Language :: Python
Classifier: Programming Language :: Python :: 3 :: Only
Classifier: Programming Language :: Python :: 3.9
Classifier: Programming Language :: Python :: 3.10
Classifier: Programming Language :: Python :: 3.11
Classifier: Programming Language :: Python :: 3.12
Classifier: Programming Language :: Python :: 3.13
Classifier: Topic :: Software Development :: Libraries :: Python Modules
Requires-Python: <3.14,>=3.9
Requires-Dist: mako<2,>=1.0.4
Requires-Dist: python-dateutil
Requires-Dist: redis<6.0,>=2.10
